[
  {
    "wikidata_qid": "Q193835",
    "imdb_id": "tt0119217",
    "tmdb_type": "movie",
    "tmdb_id": 489,
    "trakt_type": "movie",
    "trakt_id": 383,
    "plex_type": "movie",
    "plex_id": "5d776826880197001ec905d0",
    "appletv_id": "umc.cmc.ljmzio5szpnhca4ydns8f99q",
    "rottentomatoes_id": "m/good_will_hunting",
    "title": "Good Will Hunting",
    "year": 1997,
    "director_qid": "Q25186",
    "director": "Gus Van Sant",
    "duration": 126,
    "tomatometer": 98
  },
  {
    "wikidata_qid": "Q201687",
    "imdb_id": "tt1013753",
    "tmdb_type": "movie",
    "tmdb_id": 10139,
    "trakt_type": "movie",
    "trakt_id": 5356,
    "plex_type": "movie",
    "plex_id": "5d776cf7594b2b001e6fdf01",
    "appletv_id": "umc.cmc.1sjkkj28k7yaobby4bdh1klye",
    "rottentomatoes_id": "m/milk",
    "title": "Milk",
    "year": 2008,
    "director_qid": "Q25186",
    "director": "Gus Van Sant",
    "duration": 128,
    "tomatometer": 93
  },
  {
    "wikidata_qid": "Q526162",
    "imdb_id": "tt0403217",
    "tmdb_type": "movie",
    "tmdb_id": 1665,
    "trakt_type": "movie",
    "trakt_id": 1108,
    "plex_type": "movie",
    "plex_id": "5d776829999c64001ec2d13f",
    "appletv_id": "umc.cmc.4aiiqkjnqlmtfrqu4o1d6v8bl",
    "rottentomatoes_id": "m/last_days",
    "title": "Last Days",
    "year": 2005,
    "director_qid": "Q25186",
    "director": "Gus Van Sant",
    "duration": 97,
    "tomatometer": 58
  },
  {
    "wikidata_qid": "Q590701",
    "imdb_id": "tt0114681",
    "tmdb_type": "movie",
    "tmdb_id": 577,
    "trakt_type": "movie",
    "trakt_id": 456,
    "plex_type": "movie",
    "plex_id": "5d776d16ad5437001f7ccc15",
    "appletv_id": "umc.cmc.5e8h77hjpotsacj3vyn0uen9h",
    "rottentomatoes_id": "m/1066712-to_die_for",
    "title": "To Die For",
    "year": 1995,
    "director_qid": "Q25186",
    "director": "Gus Van Sant",
    "duration": 102,
    "tomatometer": 88
  },
  {
    "wikidata_qid": "Q979196",
    "imdb_id": "tt0155975",
    "tmdb_type": "movie",
    "tmdb_id": 11252,
    "trakt_type": "movie",
    "trakt_id": 6374,
    "plex_type": "movie",
    "plex_id": "5d776836999c64001ec2f826",
    "appletv_id": "umc.cmc.5zlc2df3ido40fiwp0onpwa8k",
    "rottentomatoes_id": "m/1084964-psycho",
    "title": "Psycho",
    "year": 1998,
    "director_qid": "Q25186",
    "director": "Gus Van Sant",
    "duration": 99,
    "tomatometer": 39
  },
  {
    "wikidata_qid": "Q1125451",
    "imdb_id": "tt0102494",
    "tmdb_type": "movie",
    "tmdb_id": 468,
    "trakt_type": "movie",
    "trakt_id": 370,
    "plex_type": "movie",
    "plex_id": "5d77682685719b001f3a0a69",
    "appletv_id": "umc.cmc.1l2mq35y11y7yni7dcb9jnqmp",
    "rottentomatoes_id": "m/my_own_private_idaho",
    "title": "My Own Private Idaho",
    "year": 1991,
    "director_qid": "Q25186",
    "director": "Gus Van Sant",
    "duration": 102,
    "tomatometer": 79
  },
  {
    "wikidata_qid": "Q1139284",
    "imdb_id": "tt0842929",
    "tmdb_type": "movie",
    "tmdb_id": 1990,
    "trakt_type": "movie",
    "trakt_id": 1351,
    "plex_type": "movie",
    "plex_id": "5d77682a3c3c2a001fbcbe07",
    "appletv_id": "umc.cmc.526d3gk65hsq1sykpdjvwyh46",
    "rottentomatoes_id": "m/paranoid_park",
    "title": "Paranoid Park",
    "year": 2007,
    "director_qid": "Q25186",
    "director": "Gus Van Sant",
    "duration": 85,
    "tomatometer": 77
  },
  {
    "wikidata_qid": "Q1140439",
    "imdb_id": "tt0181536",
    "tmdb_type": "movie",
    "tmdb_id": 711,
    "trakt_type": "movie",
    "trakt_id": 583,
    "plex_type": "movie",
    "plex_id": "5d7768287e9a3c0020c6ad23",
    "appletv_id": "umc.cmc.4ro6byu1k4vf4fxetuubqrdnq",
    "rottentomatoes_id": "m/finding_forrester",
    "title": "Finding Forrester",
    "year": 2000,
    "director_qid": "Q25186",
    "director": "Gus Van Sant",
    "duration": 136,
    "tomatometer": 74
  },
  {
    "wikidata_qid": "Q17459558",
    "imdb_id": "tt3450900",
    "tmdb_type": "movie",
    "tmdb_id": 291351,
    "trakt_type": "movie",
    "trakt_id": 188189,
    "plex_type": "movie",
    "plex_id": "5d776b1ead5437001f793c9f",
    "appletv_id": "umc.cmc.4zo7elfwyexowpi3gwrwdwev8",
    "rottentomatoes_id": "m/the_sea_of_trees",
    "title": "The Sea of Trees",
    "year": 2015,
    "director_qid": "Q25186",
    "director": "Gus Van Sant",
    "duration": 110,
    "tomatometer": 17
  },
  {
    "wikidata_qid": "Q28912377",
    "imdb_id": "tt6288124",
    "tmdb_type": "movie",
    "tmdb_id": 443009,
    "trakt_type": "movie",
    "trakt_id": 288496,
    "plex_type": "movie",
    "plex_id": "5d776cb7fb0d55001f5908d1",
    "appletv_id": "umc.cmc.2q1lhbvg9mi946hy8akkvmiur",
    "rottentomatoes_id": "m/dont_worry_he_wont_get_far_on_foot",
    "title": "Don't Worry, He Won't Get Far on Foot",
    "year": 2018,
    "director_qid": "Q25186",
    "director": "Gus Van Sant",
    "duration": 113,
    "tomatometer": 77
  }
]
