[
  {
    "wikidata_qid": "Q102225",
    "imdb_id": "tt0330373",
    "tmdb_type": "movie",
    "tmdb_id": 674,
    "trakt_type": "movie",
    "trakt_id": 548,
    "plex_type": "movie",
    "plex_id": "5d77682785719b001f3a0d8b",
    "appletv_id": "umc.cmc.24y16k16f8dxl4o2e8ho0lc1t",
    "rottentomatoes_id": "m/harry_potter_and_the_goblet_of_fire",
    "title": "Harry Potter and the Goblet of Fire",
    "year": 2005,
    "director_qid": "Q312088",
    "director": "Mike Newell",
    "duration": 151,
    "tomatometer": 88
  },
  {
    "wikidata_qid": "Q245172",
    "imdb_id": "tt0473075",
    "tmdb_type": "movie",
    "tmdb_id": 9543,
    "trakt_type": "movie",
    "trakt_id": 4821,
    "plex_type": "movie",
    "plex_id": "5d776833f59e580021898854",
    "appletv_id": "umc.cmc.20ya9rckijldj8c3de8luwgjp",
    "rottentomatoes_id": "m/prince_of_persia_sands_of_time",
    "title": "Prince of Persia: The Sands of Time",
    "year": 2010,
    "director_qid": "Q312088",
    "director": "Mike Newell",
    "duration": 116,
    "tomatometer": 37
  },
  {
    "wikidata_qid": "Q738456",
    "imdb_id": "tt0119008",
    "tmdb_type": "movie",
    "tmdb_id": 9366,
    "trakt_type": "movie",
    "trakt_id": 4657,
    "plex_type": "movie",
    "plex_id": "5d7768325af944001f1f9436",
    "appletv_id": "umc.cmc.1kz91b4lhhgq3ixurku7dy7tf",
    "rottentomatoes_id": "m/donnie_brasco",
    "title": "Donnie Brasco",
    "year": 1997,
    "director_qid": "Q312088",
    "director": "Mike Newell",
    "duration": 123,
    "tomatometer": 88
  }
]
