[
  {
    "wikidata_qid": "Q44408",
    "imdb_id": "tt0090793",
    "tmdb_type": "movie",
    "tmdb_id": 19492,
    "trakt_type": "movie",
    "trakt_id": 11994,
    "rottentomatoes_id": "m/captain_eo",
    "title": "Captain EO",
    "year": 1986,
    "director_qid": "Q56094",
    "director": "Francis Ford Coppola",
    "duration": 17
  },
  {
    "wikidata_qid": "Q47703",
    "imdb_id": "tt0068646",
    "tmdb_type": "movie",
    "tmdb_id": 238,
    "trakt_type": "movie",
    "trakt_id": 196,
    "plex_type": "movie",
    "plex_id": "5d7768248a7581001f12bc72",
    "appletv_id": "umc.cmc.3ew9fykdnpfaq9t2jq5da011c",
    "rottentomatoes_id": "m/the_godfather",
    "title": "The Godfather",
    "year": 1972,
    "director_qid": "Q56094",
    "director": "Francis Ford Coppola",
    "duration": 175,
    "tomatometer": 97
  },
  {
    "wikidata_qid": "Q107325",
    "imdb_id": "tt0103874",
    "tmdb_type": "movie",
    "tmdb_id": 6114,
    "trakt_type": "movie",
    "trakt_id": 3489,
    "plex_type": "movie",
    "plex_id": "5d776830961905001eb92f31",
    "appletv_id": "umc.cmc.2601qa443m4efb0452g7a0s91",
    "rottentomatoes_id": "m/bram_stokers_dracula",
    "title": "Bram Stoker's Dracula",
    "year": 1993,
    "director_qid": "Q56094",
    "director": "Francis Ford Coppola",
    "duration": 128,
    "tomatometer": 75
  },
  {
    "wikidata_qid": "Q184768",
    "imdb_id": "tt0071562",
    "tmdb_type": "movie",
    "tmdb_id": 240,
    "trakt_type": "movie",
    "trakt_id": 198,
    "plex_type": "movie",
    "plex_id": "5d776824961905001eb908e2",
    "appletv_id": "umc.cmc.3jyv977h8msmkkuz4r1u29lel",
    "rottentomatoes_id": "m/godfather_part_ii",
    "title": "The Godfather Part II",
    "year": 1974,
    "director_qid": "Q56094",
    "director": "Francis Ford Coppola",
    "duration": 202,
    "tomatometer": 96
  },
  {
    "wikidata_qid": "Q202326",
    "imdb_id": "tt0099674",
    "tmdb_type": "movie",
    "tmdb_id": 242,
    "trakt_type": "movie",
    "trakt_id": 200,
    "plex_type": "movie",
    "plex_id": "5d7768257228e5001f1dccce",
    "appletv_id": "umc.cmc.5t90r6dhxiieui9jdeajph0w4",
    "rottentomatoes_id": "m/godfather_part_iii",
    "title": "The Godfather Part III",
    "year": 1990,
    "director_qid": "Q56094",
    "director": "Francis Ford Coppola",
    "duration": 162,
    "tomatometer": 68
  },
  {
    "wikidata_qid": "Q553194",
    "imdb_id": "tt0481797",
    "tmdb_type": "movie",
    "tmdb_id": 7797,
    "trakt_type": "movie",
    "trakt_id": 3958,
    "appletv_id": "umc.cmc.6z3wl83cuqsdxcui5gbvxqitu",
    "rottentomatoes_id": "m/youth_without_youth",
    "title": "Youth Without Youth",
    "year": 2007,
    "director_qid": "Q56094",
    "director": "Francis Ford Coppola",
    "duration": 124,
    "tomatometer": 33
  },
  {
    "wikidata_qid": "Q639387",
    "imdb_id": "tt0087089",
    "tmdb_type": "movie",
    "tmdb_id": 2148,
    "trakt_type": "movie",
    "trakt_id": 1490,
    "appletv_id": "umc.cmc.5rlirt68dx9bas0ybtxlag2rm",
    "rottentomatoes_id": "m/cotton_club",
    "title": "The Cotton Club",
    "year": 1984,
    "director_qid": "Q56094",
    "director": "Francis Ford Coppola",
    "duration": 123,
    "tomatometer": 77
  },
  {
    "wikidata_qid": "Q785351",
    "imdb_id": "tt0119978",
    "tmdb_type": "movie",
    "tmdb_id": 11975,
    "trakt_type": "movie",
    "trakt_id": 6988,
    "plex_type": "movie",
    "plex_id": "5d9f3500ca3253001ef27a34",
    "appletv_id": "umc.cmc.4byyhn6mmefvo4xjjhq2asq6n",
    "rottentomatoes_id": "m/1080867-rainmaker",
    "title": "The Rainmaker",
    "year": 1997,
    "director_qid": "Q56094",
    "director": "Francis Ford Coppola",
    "duration": 135,
    "tomatometer": 82
  },
  {
    "wikidata_qid": "Q845102",
    "imdb_id": "tt0086216",
    "tmdb_type": "movie",
    "tmdb_id": 232,
    "trakt_type": "movie",
    "trakt_id": 190,
    "appletv_id": "umc.cmc.6ae2qwshdg0kq37wdtd214kpa",
    "rottentomatoes_id": "m/rumble_fish",
    "title": "Rumble Fish",
    "year": 1983,
    "director_qid": "Q56094",
    "director": "Francis Ford Coppola",
    "duration": 91,
    "tomatometer": 74
  },
  {
    "wikidata_qid": "Q858584",
    "imdb_id": "tt0061209",
    "tmdb_type": "movie",
    "tmdb_id": 42728,
    "trakt_type": "movie",
    "trakt_id": 28593,
    "rottentomatoes_id": "m/youre_a_big_boy_now",
    "title": "You're a Big Boy Now",
    "year": 1966,
    "director_qid": "Q56094",
    "director": "Francis Ford Coppola",
    "duration": 97,
    "tomatometer": 82
  },
  {
    "wikidata_qid": "Q903257",
    "imdb_id": "tt0091738",
    "tmdb_type": "movie",
    "tmdb_id": 10013,
    "trakt_type": "movie",
    "trakt_id": 5238,
    "appletv_id": "umc.cmc.3mthb50icxru8pb4rwzwk5p8u",
    "rottentomatoes_id": "m/peggy_sue_got_married",
    "title": "Peggy Sue Got Married",
    "year": 1986,
    "director_qid": "Q56094",
    "director": "Francis Ford Coppola",
    "duration": 98,
    "tomatometer": 86
  },
  {
    "wikidata_qid": "Q1009788",
    "imdb_id": "tt0071360",
    "tmdb_type": "movie",
    "tmdb_id": 592,
    "trakt_type": "movie",
    "trakt_id": 470,
    "plex_type": "movie",
    "plex_id": "5d7768273c3c2a001fbcb12e",
    "appletv_id": "umc.cmc.62px41nem3ipkv4em81sxyyow",
    "rottentomatoes_id": "m/the_conversation",
    "title": "The Conversation",
    "year": 1974,
    "director_qid": "Q56094",
    "director": "Francis Ford Coppola",
    "duration": 109,
    "tomatometer": 96
  },
  {
    "wikidata_qid": "Q1055332",
    "imdb_id": "tt0086066",
    "tmdb_type": "movie",
    "tmdb_id": 227,
    "trakt_type": "movie",
    "trakt_id": 186,
    "plex_type": "movie",
    "plex_id": "5d77682454f42c001f8c24c5",
    "appletv_id": "umc.cmc.75uhk2e0nfsgmx33t69tm55ip",
    "rottentomatoes_id": "m/outsiders",
    "title": "The Outsiders",
    "year": 1983,
    "director_qid": "Q56094",
    "director": "Francis Ford Coppola",
    "duration": 87,
    "tomatometer": 63
  },
  {
    "wikidata_qid": "Q1185312",
    "imdb_id": "tt0056983",
    "tmdb_type": "movie",
    "tmdb_id": 28503,
    "trakt_type": "movie",
    "trakt_id": 17785,
    "appletv_id": "umc.cmc.5d6whnp20ahongv8gsckmkhcf",
    "rottentomatoes_id": "m/dementia_13",
    "title": "Dementia 13",
    "year": 1963,
    "director_qid": "Q56094",
    "director": "Francis Ford Coppola",
    "duration": 81,
    "tomatometer": 67
  },
  {
    "wikidata_qid": "Q1198750",
    "imdb_id": "tt0062974",
    "tmdb_type": "movie",
    "tmdb_id": 42622,
    "trakt_type": "movie",
    "trakt_id": 28491,
    "appletv_id": "umc.cmc.7j834gito0eaefnzr9tr5jr2l",
    "rottentomatoes_id": "m/finians_rainbow",
    "title": "Finian's Rainbow",
    "year": 1968,
    "director_qid": "Q56094",
    "director": "Francis Ford Coppola",
    "duration": 144,
    "tomatometer": 53
  },
  {
    "wikidata_qid": "Q1199648",
    "imdb_id": "tt0093073",
    "tmdb_type": "movie",
    "tmdb_id": 28368,
    "trakt_type": "movie",
    "trakt_id": 17675,
    "appletv_id": "umc.cmc.645ax15iw36fnnqvwwl0setfg",
    "rottentomatoes_id": "m/gardens_of_stone",
    "title": "Gardens of Stone",
    "year": 1987,
    "director_qid": "Q56094",
    "director": "Francis Ford Coppola",
    "duration": 107,
    "tomatometer": 47
  },
  {
    "wikidata_qid": "Q1307044",
    "imdb_id": "tt0084445",
    "tmdb_type": "movie",
    "tmdb_id": 41291,
    "trakt_type": "movie",
    "trakt_id": 27290,
    "appletv_id": "umc.cmc.1b7uw4t9yaz32g34j6r3hv5eq",
    "rottentomatoes_id": "m/one_from_the_heart",
    "title": "One from the Heart",
    "year": 1982,
    "director_qid": "Q56094",
    "director": "Francis Ford Coppola",
    "duration": 108,
    "tomatometer": 50
  },
  {
    "wikidata_qid": "Q1421355",
    "imdb_id": "tt0096316",
    "tmdb_type": "movie",
    "tmdb_id": 28176,
    "trakt_type": "movie",
    "trakt_id": 17509,
    "appletv_id": "umc.cmc.1f1gggbu09bfod0zgug5503wl",
    "rottentomatoes_id": "m/tucker_the_man_and_his_dream",
    "title": "Tucker: The Man and His Dream",
    "year": 1988,
    "director_qid": "Q56094",
    "director": "Francis Ford Coppola",
    "duration": 105,
    "tomatometer": 82
  },
  {
    "wikidata_qid": "Q1471358",
    "imdb_id": "tt0116669",
    "tmdb_type": "movie",
    "tmdb_id": 7095,
    "trakt_type": "movie",
    "trakt_id": 3823,
    "plex_type": "movie",
    "plex_id": "5d776831999c64001ec2e639",
    "appletv_id": "umc.cmc.4a93v9ozn7js9f3jzm3va55ss",
    "rottentomatoes_id": "m/1072875-jack",
    "title": "Jack",
    "year": 1996,
    "director_qid": "Q56094",
    "director": "Francis Ford Coppola",
    "duration": 109,
    "tomatometer": 17
  },
  {
    "wikidata_qid": "Q2309964",
    "imdb_id": "tt0964185",
    "tmdb_type": "movie",
    "tmdb_id": 11928,
    "trakt_type": "movie",
    "trakt_id": 6943,
    "plex_type": "movie",
    "plex_id": "5d776837961905001eb94a0f",
    "appletv_id": "umc.cmc.2w69hu61vqpa691ce8j270kf3",
    "rottentomatoes_id": "m/tetro",
    "title": "Tetro",
    "year": 2009,
    "director_qid": "Q56094",
    "director": "Francis Ford Coppola",
    "duration": 127,
    "tomatometer": 71
  },
  {
    "wikidata_qid": "Q2408534",
    "imdb_id": "tt1756851",
    "tmdb_type": "movie",
    "tmdb_id": 78381,
    "trakt_type": "movie",
    "trakt_id": 58034,
    "rottentomatoes_id": "m/twixt",
    "title": "Twixt",
    "year": 2011,
    "director_qid": "Q56094",
    "director": "Francis Ford Coppola",
    "duration": 89,
    "tomatometer": 26
  },
  {
    "wikidata_qid": "Q2547631",
    "imdb_id": "tt0064873",
    "tmdb_type": "movie",
    "tmdb_id": 59231,
    "trakt_type": "movie",
    "trakt_id": 42438,
    "appletv_id": "umc.cmc.9cq73rs2ics1mszdq300t93y",
    "rottentomatoes_id": "m/rain_people",
    "title": "The Rain People",
    "year": 1969,
    "director_qid": "Q56094",
    "director": "Francis Ford Coppola",
    "duration": 102,
    "tomatometer": 83
  },
  {
    "wikidata_qid": "Q3620669",
    "imdb_id": "tt0078788",
    "tmdb_type": "movie",
    "tmdb_id": 28,
    "trakt_type": "movie",
    "trakt_id": 23,
    "plex_type": "movie",
    "plex_id": "5d77682454c0f0001f301a45",
    "appletv_id": "umc.cmc.3j20sjgobmsiwiiub94jmt3mq",
    "rottentomatoes_id": "m/apocalypse_now_redux_2001",
    "title": "Apocalypse Now Redux",
    "year": 2001,
    "director_qid": "Q56094",
    "director": "Francis Ford Coppola",
    "duration": 203,
    "tomatometer": 93
  },
  {
    "wikidata_qid": "Q3993102",
    "imdb_id": "tt0153167",
    "tmdb_type": "movie",
    "tmdb_id": 152417,
    "trakt_type": "movie",
    "trakt_id": 99834,
    "title": "Tonight for Sure",
    "year": 1962,
    "director_qid": "Q56094",
    "director": "Francis Ford Coppola",
    "duration": 69
  },
  {
    "wikidata_qid": "Q4243278",
    "imdb_id": "tt0150742",
    "tmdb_type": "movie",
    "tmdb_id": 364150,
    "trakt_type": "movie",
    "trakt_id": 370981,
    "title": "The Godfather Trilogy: 1901-1980",
    "year": 1992,
    "director_qid": "Q56094",
    "director": "Francis Ford Coppola",
    "duration": 583
  }
]
