[
  {
    "wikidata_qid": "Q151881",
    "imdb_id": "tt0313443",
    "tmdb_type": "movie",
    "tmdb_id": 2116,
    "trakt_type": "movie",
    "trakt_id": 1464,
    "plex_type": "movie",
    "plex_id": "5d776d1851dd69001fe3fe4a",
    "appletv_id": "umc.cmc.37cxdtff59srg94mg7gdro96l",
    "rottentomatoes_id": "m/out_of_time",
    "title": "Out of Time",
    "year": 2003,
    "director_qid": "Q643246",
    "director": "Carl Franklin",
    "duration": 105,
    "tomatometer": 64
  },
  {
    "wikidata_qid": "Q1111969",
    "imdb_id": "tt0257756",
    "tmdb_type": "movie",
    "tmdb_id": 11560,
    "trakt_type": "movie",
    "trakt_id": 6640,
    "plex_type": "movie",
    "plex_id": "5d7768377228e5001f1ded61",
    "appletv_id": "umc.cmc.1mv2tyk8cc9qrfb1pvwcytf3k",
    "rottentomatoes_id": "m/high_crimes",
    "title": "High Crimes",
    "year": 2002,
    "director_qid": "Q643246",
    "director": "Carl Franklin",
    "duration": 110,
    "tomatometer": 31
  },
  {
    "wikidata_qid": "Q1850866",
    "imdb_id": "tt0112857",
    "tmdb_type": "movie",
    "tmdb_id": 8512,
    "trakt_type": "movie",
    "trakt_id": 4230,
    "plex_type": "movie",
    "plex_id": "5d7768314de0ee001fccaadd",
    "appletv_id": "umc.cmc.3x5xr3ymgbykiitb91dsz1olc",
    "rottentomatoes_id": "m/devil_in_a_blue_dress",
    "title": "Devil in a Blue Dress",
    "year": 1995,
    "director_qid": "Q643246",
    "director": "Carl Franklin",
    "duration": 97,
    "tomatometer": 89
  }
]
